jamp/Jambase
jamp/Jamfile
jamp/__init__.py
jamp/__main__.py
jamp/build.py
jamp/classes.py
jamp/compile.py
jamp/executors.py
jamp/expand.py
jamp/headers.py
jamp/jam_builtins.py
jamp/jam_lexer.py
jamp/jam_syntax.py
jamp/ninja_syntax.py
jamp/paths.py
jamp/pattern.py
jamp/yacc.py
jam_build-0.7.2.dist-info/METADATA
jam_build-0.7.2.dist-info/WHEEL
jam_build-0.7.2.dist-info/entry_points.txt
jam_build-0.7.2.dist-info/licenses/LICENSE
jam_build-0.7.2.dist-info/RECORD
