Metadata-Version: 2.4
Name: jam-build
Version: 0.7.2
Summary: Jam Build System (based on Python)
Project-URL: Homepage, https://github.com/ildus/jamp
Project-URL: Issues, https://github.com/ildus/jamp/issues
Author-email: Ildus Kurbangaliev <i.kurbangaliev@gmail.com>
License-File: LICENSE
Classifier: License :: OSI Approved :: MIT License
Classifier: Operating System :: OS Independent
Classifier: Programming Language :: Python :: 3
Requires-Python: >=3.10
Provides-Extra: tests
Requires-Dist: pytest>=8.3.3; extra == 'tests'
